[
  {
    "Heading": "GSBB Interns Recruitment 2022",
    "Short": "GSBB",
    "Org": "Goa State Biodiversity Board",
    "Title": "Interns",
    "Number": "05",
    "URL": "https://www.goa.gov.in/wp-content/uploads/2022/09/Advertisement-for-appointment-of-Interns-at-GSBB.pdf",
    "Validdate": "17 October 2022"
  },
  {
    "Short": "CPCB",
    "Org": "Central Pollution Control Board",
    "Title": "Scientific Assistant, Law Officer, & Others",
    "Number": "14",
    "URL": "https://cpcb.nic.in/openpdffile.php?id=Q2FyZWVyRmlsZXMvMjE0XzE2NjM1NzkzNjZfbWVkaWFwaG90bzI4NTE5LnBkZg==",
    "Validdate": "17 October 2022"
  }
]
